embedl_hub/__init__.py
embedl_hub/cli/app.py
embedl_hub/cli/auth.py
embedl_hub/cli/benchmark.py
embedl_hub/cli/compile.py
embedl_hub/cli/helper.py
embedl_hub/cli/init.py
embedl_hub/cli/list_devices.py
embedl_hub/cli/quantize.py
embedl_hub/cli/utils.py
embedl_hub/core/__init__.py
embedl_hub/core/context.py
embedl_hub/core/hub_logging.py
embedl_hub/core/benchmark/__init__.py
embedl_hub/core/benchmark/abc.py
embedl_hub/core/benchmark/embedl.py
embedl_hub/core/benchmark/qai_hub.py
embedl_hub/core/compile/__init__.py
embedl_hub/core/compile/abc.py
embedl_hub/core/compile/onnx_to_tf.py
embedl_hub/core/compile/qai_hub.py
embedl_hub/core/hardware/__init__.py
embedl_hub/core/hardware/embedl.py
embedl_hub/core/hardware/qai_hub.py
embedl_hub/core/quantize/__init__.py
embedl_hub/core/quantize/abc.py
embedl_hub/core/quantize/calibration_data.py
embedl_hub/core/quantize/psnr.py
embedl_hub/core/quantize/qai_hub.py
embedl_hub/core/quantize/tflite.py
embedl_hub/core/utils/__init__.py
embedl_hub/core/utils/onnx_utils.py
embedl_hub/core/utils/qai_hub_utils.py
embedl_hub/core/utils/tflite_utils.py
embedl_hub/core/utils/tracking_utils.py
embedl_hub/tracking/__init__.py
embedl_hub/tracking/client.py
embedl_hub/tracking/device_cloud.py
embedl_hub/tracking/errors.py
embedl_hub/tracking/job.py
embedl_hub/tracking/rest_api.py
embedl_hub/tracking/utils.py
embedl_hub-2025.12.1.dist-info/licenses/LICENSE
embedl_hub-2025.12.1.dist-info/licenses/NOTICE
embedl_hub-2025.12.1.dist-info/METADATA
embedl_hub-2025.12.1.dist-info/WHEEL
embedl_hub-2025.12.1.dist-info/entry_points.txt
embedl_hub-2025.12.1.dist-info/top_level.txt
embedl_hub-2025.12.1.dist-info/RECORD
